{
  "db_name": "PostgreSQL",
  "query": "\n                insert into alpaca_position(dtg, symbol, exchange, asset_class, avg_entry_price, qty, qty_available, side, market_value\n                    , cost_basis, unrealized_pl, unrealized_plpc, current_price, lastday_price, change_today, asset_id)\n                values\n                    (\n                        now(),$1,$2,$3,$4,$5,$6,$7,$8,$9,$10,$11, $12, $13, $14, $15\n                    )",
  "describe": {
    "columns": [],
    "parameters": {
      "Left": [
        "Varchar",
        "Varchar",
        "Varchar",
        "Numeric",
        "Numeric",
        "Numeric",
        "Varchar",
        "Numeric",
        "Numeric",
        "Numeric",
        "Numeric",
        "Numeric",
        "Numeric",
        "Numeric",
        "Varchar"
      ]
    },
    "nullable": []
  },
  "hash": "2f8936d3543db55cc50dcb2c09d29bb2e43bb6fbaaced1b57d3df6553960f68b"
}
